[
    {
        "medico": "Marianela Bobbiesi",
        "hora": "17.36",
        "fecha": "2025-07-08",
        "dni_paciente": "40009987",
        "estado": "atendido",
        "hora_recepcion": "16:32",
        "hora_sala_espera": "16:33",
        "pago_registrado": true,
        "monto_pagado": 10000.0
    },
    {
        "medico": "Marianela Bobbiesi",
        "hora": "17:35",
        "fecha": "2025-07-08",
        "dni_paciente": "40022695",
        "estado": "atendido",
        "hora_recepcion": "16:33",
        "hora_sala_espera": "16:33",
        "pago_registrado": true,
        "monto_pagado": 15000.0
    },
    {
        "medico": "Marianela Bobbiesi",
        "hora": "17:30",
        "fecha": "2025-07-08",
        "dni_paciente": "38099876",
        "estado": "atendido",
        "hora_recepcion": "17:01",
        "hora_sala_espera": "17:01",
        "pago_registrado": true,
        "monto_pagado": 0.0
    },
    {
        "medico": "Juan Julian",
        "hora": "14:40",
        "fecha": "2025-07-11",
        "dni_paciente": "234343443|",
        "estado": "atendido",
        "hora_recepcion": "00:23",
        "hora_sala_espera": "00:23",
        "pago_registrado": true,
        "monto_pagado": 0.0
    },
    {
        "medico": "Marianela Bobbiesi",
        "hora": "09:50",
        "fecha": "2025-07-10",
        "dni_paciente": "1231414",
        "estado": "sala de espera",
        "hora_recepcion": "00:18",
        "hora_sala_espera": "00:18",
        "pago_registrado": true,
        "monto_pagado": 0.0
    },
    {
        "medico": "Marianela Bobbiesi",
        "hora": "09:00",
        "fecha": "2025-07-10",
        "dni_paciente": "38099876",
        "estado": "sala de espera",
        "hora_recepcion": "00:18",
        "hora_sala_espera": "00:18",
        "pago_registrado": true,
        "monto_pagado": 0.0
    },
    {
        "medico": "Marianela Bobbiesi",
        "hora": "09:10",
        "fecha": "2025-07-10",
        "dni_paciente": "40022695",
        "estado": "sala de espera",
        "hora_recepcion": "00:18",
        "hora_sala_espera": "00:18",
        "pago_registrado": true,
        "monto_pagado": 0.0
    },
    {
        "medico": "Francisco Colom",
        "hora": "14:30",
        "fecha": "2025-07-11",
        "dni_paciente": "2234323",
        "estado": "atendido",
        "hora_recepcion": "00:28",
        "hora_sala_espera": "00:28",
        "pago_registrado": true,
        "monto_pagado": 5000.0
    },
    {
        "medico": "Francisco Colom",
        "hora": "14:35",
        "fecha": "2025-07-11",
        "dni_paciente": "46789546",
        "estado": "atendido",
        "hora_recepcion": "00:32",
        "hora_sala_espera": "00:32",
        "pago_registrado": true,
        "monto_pagado": 0.0
    },
    {
        "medico": "Francisco Colom",
        "hora": "14:20",
        "fecha": "2025-07-11",
        "dni_paciente": "37863139",
        "estado": "atendido",
        "hora_recepcion": "02:46",
        "hora_sala_espera": "02:46",
        "pago_registrado": true,
        "monto_pagado": 0.0
    },
    {
        "medico": "Julieta Colom",
        "hora": "14:25",
        "fecha": "2025-07-11",
        "dni_paciente": "38099876",
        "estado": "sala de espera",
        "hora_recepcion": "05:03",
        "hora_sala_espera": "13:46",
        "pago_registrado": true,
        "monto_pagado": 0.0
    },
    {
        "medico": "Francisco Colom",
        "hora": "16:20",
        "fecha": "2025-07-11",
        "dni_paciente": "38099876",
        "estado": "atendido",
        "hora_recepcion": "05:04",
        "hora_sala_espera": "13:47",
        "pago_registrado": true,
        "monto_pagado": 6000.0
    },
    {
        "medico": "Julieta Colom",
        "hora": "14:15",
        "fecha": "2025-07-09",
        "dni_paciente": "38099876",
        "estado": "sala de espera",
        "hora_recepcion": "05:30",
        "hora_sala_espera": "05:30",
        "pago_registrado": true,
        "monto_pagado": 12133.0
    },
    {
        "medico": "Julieta Colom",
        "hora": "14:15",
        "fecha": "2025-07-11",
        "dni_paciente": "38099876",
        "estado": "recepcionado",
        "hora_recepcion": "13:47"
    },
    {
        "medico": "Francisco Colom",
        "hora": "14:25",
        "fecha": "2025-07-11",
        "dni_paciente": "1232423423",
        "estado": "sala de espera",
        "hora_recepcion": "16:28",
        "hora_sala_espera": "16:29",
        "pago_registrado": true,
        "monto_pagado": 6000.0
    },
    {
        "medico": "Julieta Colom",
        "hora": "17:40",
        "fecha": "2025-07-11",
        "dni_paciente": "2234323",
        "estado": "atendido",
        "hora_recepcion": "16:31",
        "hora_sala_espera": "16:31",
        "pago_registrado": true,
        "monto_pagado": 45.0
    },
    {
        "medico": "Julieta Colom",
        "hora": "17:45",
        "fecha": "2025-07-11",
        "dni_paciente": "12323423",
        "estado": "sin atender"
    },
    {
        "medico": "Marianela Bobbiesi",
        "hora": "09:00",
        "fecha": "2025-07-14",
        "dni_paciente": "37863139",
        "estado": "sin atender"
    },
    {
        "medico": "Marianela Bobbiesi",
        "hora": "09:30",
        "fecha": "2025-07-14",
        "dni_paciente": "40022695",
        "estado": "sala de espera",
        "hora_recepcion": "09:15",
        "hora_sala_espera": "23:00",
        "pago_registrado": true,
        "monto_pagado": 5000.0
    },
    {
        "medico": "Francisco Colom",
        "hora": "10:00",
        "fecha": "2025-07-14",
        "dni_paciente": "38099876",
        "estado": "sin atender"
    },
    {
        "medico": "Francisco Colom",
        "hora": "10:30",
        "fecha": "2025-07-14",
        "dni_paciente": "40082181",
        "estado": "sala de espera",
        "hora_recepcion": "10:20",
        "hora_sala_espera": "23:00",
        "pago_registrado": true,
        "monto_pagado": 3000.0
    },
    {
        "medico": "Julieta Colom",
        "hora": "11:00",
        "fecha": "2025-07-14",
        "dni_paciente": "23232323",
        "estado": "sin atender"
    }
]